search_api_webui/__init__.py
search_api_webui/app.py
search_api_webui/providers.yaml
search_api_webui/ruff.toml
search_api_webui/providers/__init__.py
search_api_webui/providers/base.py
search_api_webui/providers/generic.py
search_api_webui/providers/querit.py
search_api_webui/static/AppIcon.icns
search_api_webui/static/AppIcon.ico
search_api_webui/static/favicon.ico
search_api_webui/static/index.html
search_api_webui/static/assets/index-BWsitD55.css
search_api_webui/static/assets/index-CEkM4WD5.js
search_api_webui-0.2.1.dist-info/METADATA
search_api_webui-0.2.1.dist-info/WHEEL
search_api_webui-0.2.1.dist-info/entry_points.txt
search_api_webui-0.2.1.dist-info/licenses/LICENSE
search_api_webui-0.2.1.dist-info/RECORD
