Metadata-Version: 2.4
Name: search-api-webui
Version: 0.2.1
Summary: A Search API WebUI for testing and comparing Querit, You, and other search providers.
Project-URL: Homepage, https://github.com/querit-ai/search-api-webui
Project-URL: Repository, https://github.com/querit-ai/search-api-webui.git
Project-URL: Issues, https://github.com/querit-ai/search-api-webui/issues
Author: querit.ai
License: MIT
License-File: LICENSE
Keywords: api,arena,benchmark,llm,querit,search,tool,webui
Classifier: Development Status :: 3 - Alpha
Classifier: Framework :: Flask
Classifier: License :: OSI Approved :: MIT License
Classifier: Programming Language :: Python :: 3
Requires-Python: >=3.8
Requires-Dist: flask-cors>=3.0.0
Requires-Dist: flask>=1.1.0
Requires-Dist: jmespath>=0.10.0
Requires-Dist: pyyaml>=5.3
Requires-Dist: querit
Requires-Dist: requests>=2.22.0
Provides-Extra: build
Requires-Dist: pyinstaller>=6.0; extra == 'build'
Provides-Extra: webview
Requires-Dist: pywebview>=5.0; extra == 'webview'
